llm_fsm/__init__.py
llm_fsm/__version__.py
llm_fsm/constants.py
llm_fsm/definitions.py
llm_fsm/expressions.py
llm_fsm/fsm.py
llm_fsm/handler_system.py
llm_fsm/llm.py
llm_fsm/llm_fsm.py
llm_fsm/logging.py
llm_fsm/main.py
llm_fsm/prompts.py
llm_fsm/utilities.py
llm_fsm/validator.py
llm_fsm/visualizer.py
llm_fsm-0.1.1.dist-info/licenses/LICENSE
llm_fsm-0.1.1.dist-info/METADATA
llm_fsm-0.1.1.dist-info/WHEEL
llm_fsm-0.1.1.dist-info/entry_points.txt
llm_fsm-0.1.1.dist-info/top_level.txt
llm_fsm-0.1.1.dist-info/RECORD
