Metadata-Version: 2.4
Name: llm-fsm
Version: 0.1.1
Summary: Finite State Machines for Large Language Models
Home-page: https://github.com/nikolasmarkou/llm-fsm
Author: Nikolas Markou
Author-email: Nikolas Markou <nikolas.markou@example.com>
License: GPL-3.0
Project-URL: Homepage, https://github.com/nikolasmarkou/llm-fsm
Project-URL: Bug Tracker, https://github.com/nikolasmarkou/llm-fsm/issues
Keywords: llm,fsm,finite state machine,language model,conversation
Classifier: Development Status :: 4 - Beta
Classifier: Intended Audience :: Developers
Classifier: License :: OSI Approved :: GNU General Public License v3 (GPLv3)
Classifier: Programming Language :: Python :: 3
Classifier: Programming Language :: Python :: 3.8
Classifier: Programming Language :: Python :: 3.9
Classifier: Programming Language :: Python :: 3.10
Classifier: Programming Language :: Python :: 3.11
Classifier: Topic :: Scientific/Engineering :: Artificial Intelligence
Requires-Python: >=3.8
License-File: LICENSE
Requires-Dist: loguru>=0.7.3
Requires-Dist: litellm>=1.68.1
Requires-Dist: pydantic>=2.11.4
Requires-Dist: python-dotenv>=1.1.0
Dynamic: author
Dynamic: home-page
Dynamic: license-file
Dynamic: requires-python
